zennews/VERSION
zennews/__init__.py
zennews/alerter/__init__.py
zennews/alerter/discord_alerter.py
zennews/alerter/discord_alerter_flavor.py
zennews/cli/__init__.py
zennews/cli/base.py
zennews/cli/constants.py
zennews/cli/sources.py
zennews/cli/utils.py
zennews/materializers/__init__.py
zennews/materializers/article_materializer.py
zennews/models/__init__.py
zennews/models/article.py
zennews/pipelines/__init__.py
zennews/pipelines/zen_news_pipeline.py
zennews/steps/__init__.py
zennews/steps/report/__init__.py
zennews/steps/report/report.py
zennews/steps/sources/__init__.py
zennews/steps/sources/bbc.py
zennews/steps/summarize/__init__.py
zennews/steps/summarize/bart_large_cnn_samsum.py
zennews-0.1.8.dist-info/entry_points.txt
zennews-0.1.8.dist-info/WHEEL
zennews-0.1.8.dist-info/METADATA
zennews-0.1.8.dist-info/RECORD
