Metadata-Version: 2.1
Name: zennews
Version: 0.1.8
Summary: ZenNews: Get summarized news on a schedule.
Home-page: https://zenml.io/project/zen-news-summarization
License: Apache-2.0
Keywords: zenml
Author: ZenML GmbH
Author-email: info@zenml.io
Requires-Python: >=3.8.0,<3.11
Classifier: License :: OSI Approved :: Apache Software License
Classifier: Programming Language :: Python :: 3
Classifier: Programming Language :: Python :: 3.8
Classifier: Programming Language :: Python :: 3.9
Requires-Dist: bbc-feeds (==2.1)
Requires-Dist: discord.py (==2.1.0)
Requires-Dist: mdutils (==1.4.0)
Requires-Dist: torch (==1.13.1)
Requires-Dist: transformers (==4.26.0)
Requires-Dist: zenml[server] (==0.32.1)
Project-URL: Repository, https://github.com/zenml-io/zenml-projects/tree/main/zen-news-summarization
